jcmath/__init__.py
jcmath/lib.py
jcmath-0.0.1.dist-info/METADATA
jcmath-0.0.1.dist-info/WHEEL
jcmath-0.0.1.dist-info/top_level.txt
jcmath-0.0.1.dist-info/RECORD
