Metadata-Version: 2.1
Name: jcmath
Version: 0.0.1
Summary: JenCat custom math library with implemented math functions
Home-page: https://github.com/jencat42/jcmath
Author: JenCat
Author-email: jeniokatutza@gmail.com
Classifier: Programming Language :: Python :: 3
Classifier: License :: OSI Approved :: MIT License
Classifier: Operating System :: OS Independent
Requires-Python: >=3.6
